oots_get/__init__.py
oots_get/constants.py
oots_get/helpers.py
oots_get/main.py
oots_get-1.2.0.dist-info/METADATA
oots_get-1.2.0.dist-info/WHEEL
oots_get-1.2.0.dist-info/entry_points.txt
oots_get-1.2.0.dist-info/licenses/AUTHORS.md
oots_get-1.2.0.dist-info/licenses/LICENSE
oots_get-1.2.0.dist-info/RECORD
