Metadata-Version: 2.3
Name: oots-get
Version: 1.2.0
Summary: Download all 'Order of the Stick' comics for local reading.
Project-URL: Pull Requests, https://github.com/gnramsay/oots-get/pulls
Project-URL: Bug Tracker, https://github.com/gnramsay/oots-get/issues
Project-URL: Changelog, https://github.com/gnramsay/oots-get/blob/main/CHANGELOG.md
Project-URL: Repository, https://github.com/gnramsay/oots-get
Author-email: Grant Ramsay <grant@gnramsay.com>
License-Expression: MIT
License-File: AUTHORS.md
License-File: LICENSE
Classifier: Development Status :: 5 - Production/Stable
Classifier: Environment :: Console
Classifier: Intended Audience :: End Users/Desktop
Classifier: License :: OSI Approved :: MIT License
Classifier: Natural Language :: English
Classifier: Programming Language :: Python :: 3
Classifier: Topic :: Utilities
Requires-Python: >=3.9
Requires-Dist: bs4==0.0.2
Requires-Dist: colorama==0.4.6
Requires-Dist: lxml==5.3.0
Requires-Dist: requests==2.32.3
Requires-Dist: rich==13.8.0
Requires-Dist: single-source>=0.4.0
Requires-Dist: termcolor==2.4.0
Requires-Dist: typer>=0.12.5
